{"Error":{"Code":null,"Message":"SQLSTATE[42S22]: Column not found: 1054 Unknown column 'UG.UserGroupIDDriver' in 'where clause'"},"Time":"Tue, 19 Oct 2021 11:54:41 +0600","Argument":{"SQL":"SELECT\t\t\tUG.*,\r\n\t\t\t\tCONCAT(UG.UserGroupName) AS UserGroupLookupCaption,\r\n\t\t\t\t'' AS _Other\r\n\r\nFROM\t\t\tsphp_usergroup AS UG\r\n\t\/*LEFT JOIN\t\tX AS Y ON Y.YID = UG.YID*\/\r\n\nWHERE UG.UserGroupIDDriver = 11 \nORDER BY UserGroupLookupCaption ASC ","Parameter":[]},"Callstack":[{"file":"C:\\xampp\\htdocs\\sphp04oct2021\\library\\object\\database\\table.php","line":115,"function":"Query","class":"sPHP\\Database","object":{},"type":"->","args":["SELECT\t\t\tUG.*,\r\n\t\t\t\tCONCAT(UG.UserGroupName) AS UserGroupLookupCaption,\r\n\t\t\t\t'' AS _Other\r\n\r\nFROM\t\t\tsphp_usergroup AS UG\r\n\t\/*LEFT JOIN\t\tX AS Y ON Y.YID = UG.YID*\/\r\n\nWHERE UG.UserGroupIDDriver = 11 \nORDER BY UserGroupLookupCaption ASC ",[],false]},{"file":"C:\\xampp\\htdocs\\VehicleRentalSystem-sPHP\\script\\management\\generic\\rentvehiclerequest.php","line":190,"function":"Get","class":"sPHP\\Database\\Table","object":{},"type":"->","args":["UG.UserGroupIDDriver = 11","UserGroupLookupCaption ASC"]}]}